pyV2DL3/VtsDataSource.py
pyV2DL3/__init__.py
pyV2DL3/_version.py
pyV2DL3/addHDUClassKeyword.py
pyV2DL3/constant.py
pyV2DL3/fillEVENTS.py
pyV2DL3/fillGTI.py
pyV2DL3/fillRESPONSE.py
pyV2DL3/genHDUList.py
pyV2DL3/generateObsHduIndex.py
pyV2DL3/version.py
pyV2DL3/_dev_version/__init__.py
pyV2DL3/_dev_version/scm_version.py
pyV2DL3/eventdisplay/DBFitsFile.py
pyV2DL3/eventdisplay/EventDisplayDataSource.py
pyV2DL3/eventdisplay/IrfExtractor.py
pyV2DL3/eventdisplay/IrfInterpolator.py
pyV2DL3/eventdisplay/__init__.py
pyV2DL3/eventdisplay/fillEVENTS.py
pyV2DL3/eventdisplay/fillRESPONSE.py
pyV2DL3/eventdisplay/util.py
pyV2DL3/script/__init__.py
pyV2DL3/script/compareFitsFiles.py
pyV2DL3/script/eventdisplay_query_runparameters.py
pyV2DL3/script/generate_index_file.py
pyV2DL3/script/v2dl3.py
pyV2DL3/script/v2dl3_for_Eventdisplay.py
pyV2DL3/script/v2dl3_for_vegas.py
pyV2DL3/tests/test_IrfExtractor.py
pyV2DL3/tests/test_addHDUClassKeyword.py
pyV2DL3/tests/test_fillRESPONSE.py
pyV2DL3/tests/test_generateObsHduIndex.py
pyV2DL3/tests/test_util.py
pyV2DL3/vegas/EffectiveAreaFile.py
pyV2DL3/vegas/VegasDataSource.py
pyV2DL3/vegas/__init__.py
pyV2DL3/vegas/fillEVENTS_not_safe.py
pyV2DL3/vegas/fillRESPONSE_not_safe.py
pyV2DL3/vegas/irfloader.py
pyV2DL3/vegas/load_vegas.py
pyV2DL3/vegas/parseSt6RunList.py
pyV2DL3/vegas/root_lib_util.py
pyV2DL3/vegas/util.py
v2dl3-0.8.1.dist-info/licenses/LICENSE
v2dl3-0.8.1.dist-info/METADATA
v2dl3-0.8.1.dist-info/WHEEL
v2dl3-0.8.1.dist-info/entry_points.txt
v2dl3-0.8.1.dist-info/top_level.txt
v2dl3-0.8.1.dist-info/RECORD
