Metadata-Version: 2.4
Name: v2dl3
Version: 0.8.1
Summary: VERITAS (VEGAS and Eventdisplay) to DL3 Converter
License: BSD 3-Clause License
Project-URL: bug tracker, https://github.com/VERITAS-Observatory/V2DL3/issues
Project-URL: documentation, https://github.com/VERITAS-Observatory/V2DL3/
Project-URL: repository, https://github.com/VERITAS-Observatory/V2DL3/
Classifier: Intended Audience :: Science/Research
Classifier: License :: OSI Approved :: BSD License
Classifier: Operating System :: OS Independent
Classifier: Programming Language :: Python :: 3 :: Only
Classifier: Programming Language :: Python :: 3.9
Classifier: Programming Language :: Python :: 3.10
Classifier: Programming Language :: Python :: 3.11
Classifier: Programming Language :: Python :: 3.12
Classifier: Programming Language :: Python :: 3.13
Classifier: Topic :: Scientific/Engineering :: Astronomy
Requires-Python: ~=3.8
License-File: LICENSE
Requires-Dist: astropy
Requires-Dist: click
Requires-Dist: numpy
Requires-Dist: pkgconfig
Requires-Dist: pyyaml
Requires-Dist: scikit-learn
Requires-Dist: scipy
Requires-Dist: tqdm
Requires-Dist: uproot
Provides-Extra: tests
Requires-Dist: pytest; extra == "tests"
Requires-Dist: pytest-cov; extra == "tests"
Dynamic: license-file
